cupcake/__init__.py
cupcake/accounts.py
cupcake/cli.py
cupcake/compiler.py
cupcake/contracts.py
cupcake/deployer.py
cupcake/installer.py
cupcake/packages.py
cupcake/providers.py
cupcake/templates.py
cupcake/transact.py
cupcake/utils.py
cupcakes-0.1.10.dist-info/LICENSE.md
cupcakes-0.1.10.dist-info/METADATA
cupcakes-0.1.10.dist-info/WHEEL
cupcakes-0.1.10.dist-info/entry_points.txt
cupcakes-0.1.10.dist-info/top_level.txt
cupcakes-0.1.10.dist-info/RECORD
