Metadata-Version: 2.1
Name: cupcakes
Version: 0.1.10
Summary: Compile, test, deploy, and interact with smart contracts
Home-page: https://github.com/0xver/cupcake
Author: Sam Larsen
License: MIT
Requires-Python: >=3.9
License-File: LICENSE.md
Requires-Dist: py-solc-x
Requires-Dist: py-evm
Requires-Dist: eth-tester
Requires-Dist: web3
Requires-Dist: PyYAML
Requires-Dist: python-dotenv
Requires-Dist: simple-term-menu
